setup.py
mylibjay2/mylibllx.py
mylibjay2.egg-info/PKG-INFO
mylibjay2.egg-info/SOURCES.txt
mylibjay2.egg-info/dependency_links.txt
mylibjay2.egg-info/top_level.txt