Metadata-Version: 1.0
Name: mylibjay2
Version: 0.0.1
Summary: just a simple test
Home-page: UNKNOWN
Author: ljx
Author-email: 261958374@qq.com
License: MIT License
Keywords: simple,test
Platform: any
